Metadata-Version: 2.4
Name: llama-index-callbacks-agentops
Version: 0.4.1
Summary: llama-index instrumentation agentops integration
Author-email: Your Name <you@example.com>
License-Expression: MIT
License-File: LICENSE
Requires-Python: <4.0,>=3.9
Requires-Dist: agentops<0.3,>=0.2.2
Requires-Dist: llama-index-core<0.15,>=0.13.0
